{
  "name": "Method",
  "id": "18",
  "description": "The Method class describes the methodology used by the intruder to perpetrate the events of the incident.  This class consists of a list of references describing the attack method and a free form description of the technique. ",
  "color": "#996633",
  "aggregates": {
    "Reference": {
      "name": "Reference",
      "id": "3",
      "multiplicity": "0..*",
      "type": null,
      "description": "A reference to a vulnerability, malware sample, advisory, or analysis of an attack technique."
    },
    "Description": {
      "name": "Description",
      "id": "2",
      "multiplicity": "0..*",
      "type": "ML_STRING",
      "description": "A free-form text description of the methodology used by the intruder."
    },
    "AdditionalData": {
      "name": "AdditionalData",
      "id": "1",
      "multiplicity": "0..*",
      "type": null,
      "description": "A mechanism by which to extend the data model."
    }
  },
  "attributes": {
    "restriction": {
      "name": "restriction",
      "id": "4",
      "multiplicity": "Optional",
      "ident": "175",
      "type": "ENUM",
      "description": "This attribute is defined in Section 3.2."
    }
  }
}
